kleis/__init__.py
kleis/config/__init__.py
kleis/config/config.py
kleis/kleis_data/__init__.py
kleis/kleis_data/models/acl-rd-tec-2.0-annotator1.1.simple-posseq.bilou.ctx1.lblgeneric.pycrfsuite
kleis/kleis_data/models/acl-rd-tec-2.0-annotator1.1.simple-posseq.bio.ctx1.lblgeneric.pycrfsuite
kleis/kleis_data/models/acl-rd-tec-2.0-annotator1.1.simple.bilou.ctx1.lblgeneric.pycrfsuite
kleis/kleis_data/models/acl-rd-tec-2.0-annotator1.1.simple.bio.ctx1.lblgeneric.pycrfsuite
kleis/kleis_data/models/acl-rd-tec-2.0-annotator1.107.simple-posseq.bilou.ctx1.lblgeneric.pycrfsuite
kleis/kleis_data/models/acl-rd-tec-2.0-annotator1.107.simple-posseq.bio.ctx1.lblgeneric.pycrfsuite
kleis/kleis_data/models/acl-rd-tec-2.0-annotator1.107.simple.bilou.ctx1.lblgeneric.pycrfsuite
kleis/kleis_data/models/acl-rd-tec-2.0-annotator1.107.simple.bio.ctx1.lblgeneric.pycrfsuite
kleis/kleis_data/models/acl-rd-tec-2.0-annotator1.11.simple-posseq.bilou.ctx1.lblgeneric.pycrfsuite
kleis/kleis_data/models/acl-rd-tec-2.0-annotator1.11.simple-posseq.bio.ctx1.lblgeneric.pycrfsuite
kleis/kleis_data/models/acl-rd-tec-2.0-annotator1.11.simple.bilou.ctx1.lblgeneric.pycrfsuite
kleis/kleis_data/models/acl-rd-tec-2.0-annotator1.11.simple.bio.ctx1.lblgeneric.pycrfsuite
kleis/kleis_data/models/acl-rd-tec-2.0-annotator1.118.simple-posseq.bilou.ctx1.lblgeneric.pycrfsuite
kleis/kleis_data/models/acl-rd-tec-2.0-annotator1.118.simple-posseq.bio.ctx1.lblgeneric.pycrfsuite
kleis/kleis_data/models/acl-rd-tec-2.0-annotator1.118.simple.bilou.ctx1.lblgeneric.pycrfsuite
kleis/kleis_data/models/acl-rd-tec-2.0-annotator1.118.simple.bio.ctx1.lblgeneric.pycrfsuite
kleis/kleis_data/models/acl-rd-tec-2.0-annotator1.12.simple-posseq.bilou.ctx1.lblgeneric.pycrfsuite
kleis/kleis_data/models/acl-rd-tec-2.0-annotator1.12.simple-posseq.bio.ctx1.lblgeneric.pycrfsuite
kleis/kleis_data/models/acl-rd-tec-2.0-annotator1.12.simple.bilou.ctx1.lblgeneric.pycrfsuite
kleis_keyphrase_extraction-0.2a1.dev3.dist-info/LICENSE
kleis_keyphrase_extraction-0.2a1.dev3.dist-info/METADATA
kleis_keyphrase_extraction-0.2a1.dev3.dist-info/WHEEL
kleis_keyphrase_extraction-0.2a1.dev3.dist-info/top_level.txt
kleis_keyphrase_extraction-0.2a1.dev3.dist-info/RECORD
