Metadata-Version: 2.1
Name: kleis-keyphrase-extraction
Version: 0.2a1.dev3
Summary: Python package for keyphrase labeling.
Home-page: https://github.com/sdhdez/kleis-keyphrase-extraction
Author: Simon D. Hernandez
Author-email: py.kleis@sdhdez.dev
License: MIT
Keywords: automatic-keyphrase-extraction keyphrase-extraction keyphrase-labeling keyword-extraction crf pos-tag-sequences
Platform: UNKNOWN
Classifier: Development Status :: 3 - Alpha
Classifier: Intended Audience :: Developers
Classifier: Topic :: Software Development :: Build Tools
Classifier: License :: OSI Approved :: MIT License
Requires-Python: >=3.5, <4
Requires-Dist: nltk
Requires-Dist: python-crfsuite
